Metadata-Version: 2.1
Name: django-admin-csvexport2
Version: 1.11
Summary: Django-admin-action to export items as csv-formatted data.
Home-page: https://github.com/brunomiglioretto/django-admin-csvexport
Author: Bruno Miglioretto
Author-email: brunomiglioretto@gmail.com
License: BSD License
Platform: OS Independent
Classifier: Development Status :: 5 - Production/Stable
Classifier: Framework :: Django
Classifier: Environment :: Web Environment
Classifier: Intended Audience :: Developers
Classifier: License :: OSI Approved :: BSD License
Classifier: Operating System :: OS Independent
Classifier: Programming Language :: Python
Classifier: Programming Language :: Python :: 3
Classifier: Programming Language :: Python :: 3.4
Classifier: Programming Language :: Python :: 3.5
Classifier: Programming Language :: Python :: 3.6
Classifier: Programming Language :: Python :: 3.7
Classifier: Programming Language :: Python :: 3.8
Classifier: Programming Language :: Python :: 3.9
Classifier: Topic :: Internet :: WWW/HTTP :: Dynamic Content
Classifier: Topic :: Software Development
Classifier: Topic :: Software Development :: Libraries :: Application Frameworks
License-File: LICENCE
Requires-Dist: Django (>=1.11)
Requires-Dist: anytree (>=2.8.0)
